Pysxmovesx.py
pysxmovesx-1.0.0.dist-info/WHEEL
pysxmovesx-1.0.0.dist-info/METADATA
pysxmovesx-1.0.0.dist-info/RECORD
